README.md
setup.cfg
setup.py
pytest_dash/__init__.py
pytest_dash/application_runners.py
pytest_dash/behavior_parser.py
pytest_dash/behaviors.py
pytest_dash/errors.py
pytest_dash/new_hooks.py
pytest_dash/plugin.py
pytest_dash/wait_for.py
pytest_dash.egg-info/PKG-INFO
pytest_dash.egg-info/SOURCES.txt
pytest_dash.egg-info/dependency_links.txt
pytest_dash.egg-info/entry_points.txt
pytest_dash.egg-info/requires.txt
pytest_dash.egg-info/top_level.txt