Metadata-Version: 2.1
Name: pytest-dash
Version: 2.1.2
Summary: pytest fixtures to run dash applications.
Home-page: https://github.com/T4rk1n/pytest-dash
Author: Philippe Duval
Author-email: philippe@plot.ly
License: MIT
Keywords: dash,plotly,pytest
Platform: UNKNOWN
Classifier: Programming Language :: Python
Classifier: Programming Language :: Python :: 2.7
Classifier: Programming Language :: Python :: 3
Classifier: Programming Language :: Python :: 3.3
Classifier: Programming Language :: Python :: 3.4
Classifier: Programming Language :: Python :: 3.5
Classifier: Programming Language :: Python :: 3.6
Classifier: Programming Language :: Python :: 3.7
Classifier: License :: OSI Approved :: MIT License
Classifier: Framework :: Pytest
Classifier: Framework :: Flask
Classifier: Intended Audience :: Developers
Classifier: Topic :: Software Development :: Testing
